llm2json/__init__.py
llm2json/output/__init__.py
llm2json/output/parser.py
llm2json/output/utils.py
llm2json/prompts/__init__.py
llm2json/prompts/schema.py
llm2json/prompts/templates.py
llm2json-0.1.0.dist-info/LICENSE.txt
llm2json-0.1.0.dist-info/METADATA
llm2json-0.1.0.dist-info/WHEEL
llm2json-0.1.0.dist-info/top_level.txt
llm2json-0.1.0.dist-info/RECORD
