Metadata-Version: 2.1
Name: llm2json
Version: 0.1.0
Summary: Web Based Multi Purpose Annotation Software
Home-page: https://github.com/JiehangXie/llm2json
Author: Jiehang Xie
Author-email: xiejiehang@foxmail.com
License: MIT License
Classifier: License :: OSI Approved :: MIT License
Classifier: Programming Language :: Python :: 3
Classifier: Natural Language :: Chinese (Simplified)
Classifier: Natural Language :: English
Requires-Python: >=3.7
License-File: LICENSE.txt
Requires-Dist: pydantic
